LICENSE.md
MANIFEST.in
README.md
setup.py
docs/blank.txt
python_stripe.egg-info/PKG-INFO
python_stripe.egg-info/SOURCES.txt
python_stripe.egg-info/dependency_links.txt
python_stripe.egg-info/not-zip-safe
python_stripe.egg-info/requires.txt
python_stripe.egg-info/top_level.txt
stripe_python/__init__.py
stripe_python/util.py
stripe_python/__pycache__/__init__.cpython-310.pyc
stripe_python/__pycache__/util.cpython-310.pyc